pylint2junit/__init__.py
pylint2junit/__main__.py
pylint2junit/junit_types.py
pylint2junit/junitreporter.py
pylint2junit/parse.py
pylint2junit/tojunit.py
pylint2junit-1.0.1.dist-info/METADATA
pylint2junit-1.0.1.dist-info/RECORD
pylint2junit-1.0.1.dist-info/WHEEL
pylint2junit-1.0.1.dist-info/entry_points.txt
pylint2junit-1.0.1.dist-info/top_level.txt
