Metadata-Version: 2.1
Name: pylint2junit
Version: 1.0.1
Summary: Converts pylint output to junit style test results
Home-page: UNKNOWN
Author: andrew.roden@crowdstrike.com
Author-email: andrew.roden@crowdstrike.com
License: BSD
Keywords: pylint
Platform: UNKNOWN
Classifier: Intended Audience :: Developers
Classifier: License :: OSI Approved :: BSD License
Classifier: Operating System :: OS Independent
Classifier: Programming Language :: Python :: 2
Classifier: Programming Language :: Python :: 2.7
Classifier: Programming Language :: Python :: 3
Classifier: Programming Language :: Python :: 3.7
